GravCap/GravCap.py
GravCap/__init__.py
src/GravCap.py
src/__init__.py
GravCap-24.0.1.dist-info/METADATA
GravCap-24.0.1.dist-info/WHEEL
GravCap-24.0.1.dist-info/entry_points.txt
GravCap-24.0.1.dist-info/top_level.txt
GravCap-24.0.1.dist-info/RECORD
